djecharts/apps.py
djecharts/core/exceptions.py
djecharts/core/filter.py
djecharts/core/utils.py
djecharts/core/view.py
djecharts/static/djecharts/css/style.css
djecharts/static/djecharts/js/main.js
djecharts/static/djecharts/js/main.js.LICENSE.txt
djecharts/templates/djecharts/echarts_card.html
djecharts/templates/djecharts/echarts_container.html
djecharts/templates/djecharts/echarts_error.html
djecharts/templates/djecharts/echarts_filter_form.html
djecharts-0.1.5.dist-info/licenses/LICENSE
djecharts-0.1.5.dist-info/METADATA
djecharts-0.1.5.dist-info/WHEEL
djecharts-0.1.5.dist-info/top_level.txt
djecharts-0.1.5.dist-info/RECORD
