Metadata-Version: 2.4
Name: djecharts
Version: 0.1.5
Summary: Django Echarts
Author-email: André Lopes <andrelopes.code@gmail.com>
Classifier: Environment :: Web Environment
Classifier: Programming Language :: Python
Classifier: Programming Language :: Python :: 3
Classifier: Operating System :: OS Independent
Classifier: License :: OSI Approved :: MIT License
Classifier: Framework :: Django
Requires-Python: >=3.12
License-File: LICENSE
Requires-Dist: django<6.0,>=4.0
Requires-Dist: django<6.0,>=4.0
Dynamic: license-file
